{
    "doc": {
        "metadata": {
            "image": [],
            "title": "",
            "description": ""
        },
        "api": {
            "method": "get",
            "url": "",
            "auth": "required",
            "results": {
                "codes": [
                    {
                        "name": "",
                        "code": "{}",
                        "language": "json",
                        "status": 200
                    },
                    {
                        "name": "",
                        "code": "{}",
                        "language": "json",
                        "status": 400
                    }
                ]
            },
            "params": []
        },
        "next": {
            "description": "",
            "pages": []
        },
        "algolia": {
            "recordCount": 24,
            "publishPending": false,
            "updatedAt": "2023-02-20T21:25:40.106Z"
        },
        "title": "FAQs",
        "icon": "",
        "updates": [],
        "type": "basic",
        "slug": "faq",
        "excerpt": "",
        "body": "### Is the hosted Reservoir API free to use?\n\nCurrently, the [hosted Reservoir API](/reference) is free to use. Register for an instant API key [here](https://docs.reservoir.tools/reference/rate-limits).\n\n### From where does Reservoir currently aggregate orders?\n\nCurrently, Reservoir aggregates sell-side orders (asks) from: \n\n- OpenSea\n- LooksRare\n- X2Y2\n- Sudoswap\n- Coinbase NFT\n- Rarible\n- Manifold Gallery\n- Foundation\n- Zora\n- Reservoir’s native applications\n\nAnd buy-side orders from:\n\n- OpenSea\n- LooksRare\n- X2Y2\n- Sudoswap\n- Rarible\n- CoinbaseNFT\n\nYou can find a more detailed breakdown [here](https://docs.reservoir.tools/docs/aggregated-liquidity).\n\n### When will you aggregate Blur?\n\nCurrently, Blur has a closed API. The moment Blur releases a public API, we will aggregate them immediately.\n\n### What listings do you support?\n\nReservoir supports fixed (Buy Now) and Dutch auctions. We do not support English auctions at this time. Dutch auction prices are updated every 10 minutes.\n\n### Do you support lazy minting NFTs?\n\nWe do not support lazy minting at this time.\n\n### What blockchains do you support?\n\nReservoir hosted API is currently available on the following chains:\n\n- Ethereum\n- Goerli (testnet)\n- Polygon (beta)\n- Optimism (beta)\n\nWe plan to roll out support for more EVM compatible chains soon.\n\n### Do you offer Mumbai (testnet)?\n\nCurrently, we only offer Goerli as a testnet. You're welcome to make a Feature Request if you'd like Mumbai support [here](https://reservoir.canny.io/feature-requests).\n\n### Do you support OpenRarity or provide a rarity score?\n\nWe do not currently use OpenRarity ranks for our api. We use PopRank's NFT rankings that you can more about [here](https://www.npmjs.com/package/@poprank/rankings).\n\nWe return both rarity and rarityRank in the tokens API (<https://docs.reservoir.tools/reference/gettokensv5>). \n\n`rarity` is a score based on the frequencies of each trait given to each token within a collection. \n\n`rarityRank` is a rank given to each each token within a collection based on their `rarity`. In most cases we recommended using `rarityRank`. \n\nNote: As `rarity` is based on trait frequency, collections with few or no traits will not provide accurate `rarity`  or `rarityRank` data.\n\n### How do you handle suspicious tokens flagged by OpenSea?\n\nOur [tokens endpoint ](https://docs.reservoir.tools/reference/gettokensv5)will return `isflagged` boolean to help developers easily identify suspicious tokens flagged by OpenSea. You can read more about this feature [here](https://docs.reservoir.tools/docs/flagged-tokens).\n\n### How do I see collection wide offers?\n\nUse our `/orders/bids/v5` and use the collection param with a collection-id. You can see the Bids API [here](https://docs.reservoir.tools/reference/getordersbidsv5) and create a collection-id [here](https://docs.reservoir.tools/reference/postcollectionssetsv1). \n\n### Why do I not see all bids(offers)?\n\nWe filter out single token bids that are 80% below the floor price. This is to reduce spam due to there being large volumes of bids with low chances of being accepted.\n\nWe show 100% of collection wide and trait wide bids.\n\n### Why don't I see mint prices listed under activity?\n\nUnfortunately we don't save the mint prices in the activities API feed, we only do it in the sales API. You're welcome to make a Feature Request for this [here](https://reservoir.canny.io/feature-requests)\n\n### Where do Reservoir native orders get distributed to?\n\nReservoir orders get distributed to any application that natively ingests orders from the aggregated orderbook. While Reservoir native orders are not automatically pushed to OpenSea, we make it possible (and easy) to publish orders into the OpenSea orderbook using our Router contract or API. \n\n### How do marketplace and royalty fees work with Reservoir?\n\nWith our easy-to-use APIs apps built on Reservoir have full control over marketplace and royalty fees. You can read more about royalties [here](https://docs.reservoir.tools/docs/royalties).\n\n### What's the difference between marketplace and referral fees?\n\nMarketplace fees are built into the order. Referral fees are taken on top when filling the order. (e.g. You could take fees on top when filling an OpenSea order that already  has a marketplace fee built-in)\n\n### What is a trait-specific bid?\n\nTrait-specific bids are bids that apply to any token that has a particular trait associated with it. A single trait-specific bid can be accepted by any holder of a token with the trait. Once your single trait-specific bid is accepted, is it considered executed, so only one sale is possible with each bid quantity, even if the bid applies to multiple tokens. Further, we allow you to create custom sets of tokens on which to bid, in a similar style to how trait-specific bids work (see the API reference [here](/reference/)) as well as create your own custom metadata for collections ( see [Metadata Engine](doc:metadata-engine)).\n\n### How do I get a Reservoir API key?\n\nRegister for an API key [here](https://docs.reservoir.tools/reference/rate-limits). If you want to just test out the API first, feel free to query without the key. \n\n### What is WETH?\n\nWrapped Ethereum (WETH) is Ethereum wrapped in the ERC-20 standard. This ERC-20 standard allows you to approve the token to be transferred, which is the fundamental mechanism by which you can place bids and have the WETH transferred out of your wallet at a later date. This is also why you need to approve your WETH for trading.\n\n### Why is it necessary to pay gas to cancel orders?\n\nYou need to pay to cancel orders because orders are signed atomic units that can be copied. If Reservoir simply deleted your order from the orderbook, there's no way to know whether someone has a signed copy of the order stored elsewhere. When you cancel an order, you are sending a transaction to the on-chain exchange contract tell it to not process your order. Since this step must be done on-chain, you need to pay gas. \n\n### How frequently is metadata automatically refreshed?\n\nToken metadata is never automatically refreshed, but may be manually refreshed [here](https://docs.reservoir.tools/reference/posttokensrefreshv1).\n\nCollection metadata is updated at 23:30 UTC daily for:\n\n- Top 500 Collection by 24hr Volume\n- Collections Minted 1 Day Ago\n- Collections Minted 7 Days Ago\n\nCollections can also be manually refreshed [here](https://docs.reservoir.tools/reference/postcollectionsrefreshv1).\n\nCaution: These APIs should be used in moderation, like only when missing data is discovered. Calling it in bulk / programmatically will result in your key getting rate limited.\n\n### Do you have any websockets?\n\nWe offer a top bids websocket (beta). You can read more about it [here](https://docs.reservoir.tools/docs/realtime-websocket-events).\n\n### What RPC provider do you use?\n\nWe use QuickNode. But when a user is purchasing, it uses their own RPC.\n\n### Where is the Reservoir router contract?\n\nThe ethereum contract address for the Reservoir router is: 0x178a86d36d89c7fdebea90b739605da7b131ff6a ([etherscan](https://etherscan.io/address/0x178a86d36d89c7fdebea90b739605da7b131ff6a))\n\n### Has the Reservoirrouter contract been audited?\n\nYes the router contract has been audited by Consensys Dilligence. You can find more details [here](https://docs.reservoir.tools/docs/security-and-smart-contract-audits).",
        "order": 4,
        "isReference": false,
        "deprecated": false,
        "hidden": false,
        "sync_unique": "",
        "link_url": "",
        "link_external": false,
        "previousSlug": "",
        "slugUpdatedAt": "2022-06-15T19:20:29.898Z",
        "revision": 34,
        "_id": "63f3e45464c04e0012a8fb35",
        "pendingAlgoliaPublish": false,
        "createdAt": "2022-06-15T20:39:05.384Z",
        "updatedAt": "2023-02-15T17:44:24.980Z",
        "user": "638528928b4b3601d2a4bf4a",
        "category": "63f3e45464c04e0012a8fb11",
        "project": "62a239ec3e4c0800663c6d05",
        "version": "63f3e45464c04e0012a8fc52",
        "__v": 0,
        "parentDoc": null,
        "isApi": false,
        "id": "63f3e45464c04e0012a8fb35"
    },
    "meta": {
        "slug": "faq",
        "type": "docs",
        "parent": null,
        "image": [],
        "title": "FAQs",
        "title_raw": "FAQs",
        "description": "Is the hosted Reservoir API free to use?Currently, the hosted Reservoir API is free to use. Register for an instant API key here.From where does Reservoir currently aggregate orders?Currently, Reservoir aggregates sell-side orders (asks) from: OpenSeaLooksRareX2Y2SudoswapCoinbase NFTRaribleManifold ...",
        "_id": "63f3e45464c04e0012a8fb35",
        "hidden": false
    },
    "activeDoc": "faq",
    "embedding": [
        0.006880392,
        -0.01782485,
        -0.0103669325,
        -0.013340117,
        -0.023015445,
        0.0030266594,
        -0.020847945,
        0.006841177,
        -0.03174249,
        -0.02017773,
        0.013739394,
        -0.0017263367,
        0.010281373,
        -0.005361715,
        0.0005547984,
        0.007301058,
        0.02602428,
        -0.024612552,
        0.01651294,
        -0.002841281,
        0.010445362,
        0.015186772,
        -0.024341615,
        -0.00065149827,
        -0.02478367,
        -0.00038746765,
        0.0356497,
        -0.008641487,
        -0.015842726,
        -0.01538641,
        0.00587507,
        0.018010227,
        -0.025510924,
        -0.019393437,
        -0.008377679,
        -0.0053795394,
        0.011678841,
        -0.007579126,
        0.0020159904,
        0.005326065,
        0.032740682,
        0.016156442,
        -0.0013974681,
        -0.0045025568,
        -0.0024954788,
        0.022744508,
        -0.0027878063,
        -0.0057609915,
        0.020748125,
        0.015871245,
        -0.0059748893,
        0.005892895,
        -0.0035114952,
        -0.011429293,
        -0.01889434,
        0.0020266853,
        -0.008570188,
        0.029974267,
        -0.007821544,
        -0.007443657,
        0.02258765,
        -0.002723637,
        -0.026423557,
        0.0053759743,
        0.008805475,
        -0.012398965,
        -0.004046241,
        0.01778207,
        -0.01303353,
        -0.02946091,
        0.014744715,
        0.00050444325,
        0.012619994,
        -0.007564866,
        0.035393022,
        -0.022159852,
        -0.01664128,
        0.00072992756,
        0.028733658,
        -0.012270627,
        0.00086227705,
        -0.004855489,
        -0.007942753,
        0.044462305,
        0.030345023,
        0.030230945,
        0.013290208,
        0.039956182,
        -0.020434408,
        -0.008762696,
        0.013660965,
        0.027849544,
        -0.0016639497,
        -0.0099248765,
        -0.014523687,
        0.008035442,
        -0.018566363,
        0.018181346,
        -0.01664128,
        -0.0151154725,
        -0.014452388,
        0.022159852,
        -0.02257339,
        -0.030173905,
        -0.038444635,
        0.0031336085,
        -0.0087840855,
        -0.019735673,
        0.009796537,
        0.031115057,
        -0.0130905695,
        0.026223918,
        -0.022901366,
        -0.024341615,
        -0.0014206405,
        0.00077359844,
        0.042009603,
        -0.031799532,
        0.003294032,
        -0.025696302,
        0.017354272,
        0.0058857654,
        0.04132513,
        -0.023086745,
        0.016042365,
        -0.010987237,
        -0.026223918,
        0.0015088735,
        -0.018010227,
        -0.033197,
        -0.0049339184,
        0.0029535776,
        0.002834151,
        0.010702039,
        0.0022013688,
        0.026608935,
        -0.021660756,
        0.0026523375,
        -0.013511236,
        -0.016826658,
        -0.0012807155,
        0.010801858,
        -0.010067475,
        -0.016812397,
        -0.011044277,
        0.028020663,
        0.018167086,
        -0.016384602,
        0.025354065,
        -0.012413225,
        -0.0012798242,
        -0.012862411,
        -0.018851561,
        0.008591577,
        -0.014053111,
        -0.00413893,
        -0.022002993,
        -0.00044406156,
        -0.0026202528,
        -0.0019660809,
        0.009846447,
        0.04768504,
        -0.00030502773,
        0.0072547137,
        -0.003392069,
        0.018623402,
        0.03199917,
        -0.015529009,
        -0.0018056572,
        -0.011564762,
        -0.011236785,
        0.011707361,
        -0.01303353,
        0.012748332,
        -0.007090725,
        0.019764192,
        0.006224437,
        -0.002525781,
        -0.018295426,
        -0.018780261,
        0.020904982,
        -0.01664128,
        0.019707153,
        0.05059405,
        -0.013824953,
        -0.04360671,
        0.01300501,
        -0.011999688,
        -0.0040747607,
        -0.012648513,
        -0.014523687,
        0.019222317,
        0.010103124,
        -0.024612552,
        -0.5936673,
        -0.034708545,
        0.011472073,
        -0.022316711,
        0.0012557607,
        -0.005361715,
        -0.0042173592,
        0.0379598,
        -0.021874655,
        0.034423348,
        0.013233168,
        0.023015445,
        -0.018623402,
        -0.026366517,
        -0.028548278,
        -0.016127924,
        0.011350864,
        -0.018609142,
        0.020462926,
        -0.018723221,
        0.009425781,
        0.034708545,
        -0.041952565,
        0.024441434,
        0.013147608,
        0.021632237,
        0.03422371,
        -0.004484732,
        0.009325962,
        -0.02010643,
        -0.024327355,
        0.028961815,
        0.0014126193,
        0.011906999,
        0.059720375,
        -0.0072796685,
        -0.014359699,
        0.03670493,
        0.012213587,
        0.050537013,
        0.013832083,
        -0.0022174113,
        0.041809965,
        -0.015685868,
        0.011165486,
        -0.0044063027,
        0.023414722,
        -0.008819736,
        0.004506122,
        0.0052440707,
        -0.012541564,
        0.006367036,
        -0.0063242563,
        0.011308084,
        0.017168894,
        -0.038530193,
        0.03530746,
        -0.003661224,
        0.0076361652,
        0.022830067,
        0.008199431,
        0.011579022,
        -0.03082986,
        -0.030516142,
        -0.03410963,
        0.018053008,
        0.004049806,
        -0.0055328333,
        0.009383,
        0.0028537584,
        0.023871038,
        0.020519966,
        0.015229551,
        0.013347247,
        -0.0038073878,
        0.020634046,
        0.024427174,
        0.009568379,
        -0.013846342,
        0.036362693,
        0.02488349,
        -0.0038002578,
        0.002017773,
        -0.0148302745,
        0.00018069941,
        0.019692894,
        0.007429397,
        -0.025710562,
        0.03653381,
        0.018024487,
        0.005793076,
        0.030230945,
        -0.013953292,
        -0.0236001,
        -0.0012994315,
        0.03416667,
        -0.017026296,
        0.018209865,
        0.008798346,
        -0.011529112,
        -0.007999793,
        -0.016370341,
        -0.0071299397,
        0.0057538613,
        0.022630429,
        0.012263496,
        -0.022801546,
        0.0050479975,
        -0.0048804437,
        0.005076517,
        -0.037674602,
        -0.018552104,
        -0.023956597,
        -0.027992142,
        0.0053545847,
        -0.038330555,
        0.03325404,
        0.023386203,
        0.020348849,
        0.017753549,
        -0.021133142,
        -0.0030961763,
        0.03818796,
        0.01537215,
        0.005554223,
        0.0030640916,
        -0.0036344868,
        -0.01888008,
        -0.011129836,
        0.02254487,
        -0.0019126063,
        -0.023300642,
        0.015143992,
        -0.018366724,
        0.0307443,
        0.011386514,
        0.0096396785,
        -0.004135365,
        -0.01055231,
        -0.0189799,
        -0.003903642,
        0.012634253,
        0.030687261,
        -0.0307443,
        -0.046572767,
        -0.010801858,
        -0.023585841,
        0.007479307,
        -0.013953292,
        0.0027771115,
        -0.013996071,
        -0.010645,
        0.018138567,
        0.02241653,
        -0.020577006,
        0.0068768268,
        -0.018680442,
        -0.022730248,
        -0.012299146,
        -0.014816015,
        -0.008641487,
        -0.01423849,
        -0.019864012,
        -0.0015605655,
        -0.0005253874,
        -0.03065874,
        -0.0013003227,
        0.009932006,
        0.0054116244,
        -0.031542853,
        -0.012805372,
        0.00074062246,
        -0.0060533187,
        0.0084347185,
        0.012619994,
        0.024184756,
        -0.014067371,
        0.005486489,
        -0.00053652795,
        -0.0006880392,
        0.0009785842,
        0.008028312,
        -0.01540067,
        -0.008049702,
        0.037703123,
        0.019079719,
        0.025682043,
        0.044005986,
        -0.009561249,
        0.030145384,
        -0.030373544,
        0.03416667,
        -0.022316711,
        0.017525392,
        -0.011229655,
        -0.023058224,
        0.014816015,
        -0.0012022861,
        0.016327562,
        0.03182805,
        0.015514749,
        0.014530817,
        -0.0050729522,
        -0.0025810383,
        -0.019536035,
        -0.011985429,
        -0.003900077,
        -0.006003409,
        0.021076102,
        0.029660549,
        0.016840918,
        -0.019764192,
        -0.0031995603,
        0.018081527,
        -0.007536346,
        -0.00055346155,
        0.010730559,
        -0.013418547,
        -0.005176336,
        0.0065132,
        -0.0026523375,
        -0.014010332,
        0.029261272,
        -0.009632548,
        -0.015785687,
        0.0037075686,
        0.0165272,
        -0.00038457112,
        -0.0038073878,
        -0.0128980605,
        0.002422397,
        0.006042624,
        0.008791216,
        0.0007143308,
        0.01655572,
        0.02013495,
        0.005657607,
        -0.0048661837,
        0.016769618,
        -0.0071691545,
        0.013397156,
        -0.009097803,
        0.011215395,
        -0.015614568,
        0.047656517,
        0.011614672,
        0.01762521,
        0.046544246,
        -0.023457501,
        0.0034633682,
        0.0056326524,
        0.010167294,
        0.006352776,
        -0.0070158606,
        0.015742907,
        -0.0070158606,
        0.017111855,
        -0.00068313733,
        0.01535789,
        -0.0009821492,
        0.028134743,
        0.012848151,
        0.020962022,
        -0.0026131228,
        0.0063385163,
        0.013233168,
        -0.009618289,
        -0.0020355978,
        -0.00033822653,
        0.008912425,
        -0.0010935545,
        -0.024070676,
        -0.02000661,
        -0.006277912,
        0.012634253,
        0.009083543,
        -0.0029018854,
        0.0006911585,
        -0.014067371,
        0.013454196,
        -0.03313996,
        -0.0261241,
        0.0378172,
        0.017382793,
        -0.006973081,
        -0.013211778,
        0.006990906,
        0.02129,
        -0.008805475,
        0.017054815,
        0.0124560045,
        0.00038880453,
        0.0012156548,
        0.0029714024,
        0.0026772923,
        -0.011521983,
        0.025125908,
        -0.016612759,
        -0.025739083,
        -0.0077716345,
        0.00021969127,
        0.012805372,
        -0.0022797983,
        -0.012078118,
        0.029346831,
        -0.01641312,
        -0.035820816,
        -0.027749725,
        0.0071370695,
        0.005165641,
        -0.012420355,
        -0.0030248768,
        -0.03425223,
        -0.013639575,
        0.018224126,
        -0.0032441225,
        -0.020377368,
        -0.0039321617,
        0.025696302,
        0.005276155,
        -0.019806972,
        -0.00024642854,
        -0.024441434,
        0.007358098,
        0.07067196,
        -0.0020748125,
        -0.010851768,
        0.018152827,
        -0.026780054,
        -0.024484213,
        -0.00711568,
        -0.0032066903,
        -0.0017824849,
        0.016384602,
        -0.008056832,
        -0.00824221,
        0.019892532,
        0.0103027625,
        0.001591759,
        -0.014495167,
        -0.021746317,
        -0.022117073,
        0.008448979,
        -0.021076102,
        0.021247221,
        -0.01306205,
        -0.018366724,
        0.044547863,
        0.036933087,
        0.00032775442,
        0.030573182,
        -0.011087056,
        0.00041598742,
        -0.02826308,
        -0.013347247,
        -0.015814206,
        0.012035338,
        0.014915834,
        0.0024241796,
        0.042123683,
        0.026323738,
        0.016070884,
        -0.0054971837,
        0.0116004115,
        0.0142598795,
        0.022245413,
        -0.0046772403,
        0.011707361,
        0.021689277,
        -0.006955256,
        -0.018438024,
        0.011621802,
        0.010730559,
        0.007664685,
        -0.018224126,
        -0.008762696,
        -0.043435592,
        -0.0033118569,
        0.0012557607,
        0.0131832585,
        0.01776781,
        0.014288399,
        -0.019307876,
        -0.052219678,
        -0.016028104,
        -0.022088554,
        -0.0032280802,
        0.004395608,
        -0.023585841,
        -0.02469811,
        -0.017268714,
        0.013789304,
        -0.0088482555,
        -0.0050622574,
        0.006256522,
        -0.009946266,
        -0.031457294,
        0.0044419523,
        0.015343631,
        0.018466543,
        0.022388011,
        0.026822833,
        0.024455693,
        -0.0059713246,
        0.011094186,
        -0.02830586,
        0.015614568,
        -0.04714316,
        -0.019921051,
        -0.004759235,
        0.026822833,
        -0.004491862,
        0.00951847,
        0.03325404,
        -0.026252437,
        -0.011942649,
        0.02134704,
        0.01778207,
        0.014088761,
        0.012406095,
        0.022801546,
        0.017468352,
        0.0079284925,
        -0.008399069,
        -0.003679049,
        -0.013603925,
        -0.0062600872,
        0.004028416,
        -0.0039998963,
        -0.0017637688,
        -0.00030814708,
        -0.0035917072,
        -0.00532963,
        0.021774836,
        -0.01909398,
        -0.012056728,
        -0.0046451557,
        -0.0056041325,
        -0.013988942,
        -0.028548278,
        -0.0129622305,
        0.014495167,
        -0.0143882185,
        0.021831876,
        -0.012227846,
        -0.02241653,
        0.028776437,
        -0.008691397,
        -0.028705137,
        -0.0023136653,
        -0.01773929,
        0.002605993,
        0.010324153,
        0.005105037,
        -0.0001658825,
        0.052390795,
        0.0017851586,
        -0.016142184,
        -0.006249392,
        -0.011286695,
        0.008698527,
        -0.008684266,
        -0.007686075,
        0.013554015,
        -0.02841994,
        -0.019621594,
        -0.0071406346,
        -0.0067092734,
        -0.021717796,
        -0.024726631,
        -0.014352568,
        -0.011514853,
        -0.0037111335,
        0.009040764,
        -0.004270834,
        0.0064312057,
        -0.02257339,
        -0.015058433,
        -0.02963203,
        -0.008028312,
        0.0064240755,
        -0.026280958,
        0.021418339,
        0.0071513294,
        -0.016940737,
        0.017069075,
        0.023913817,
        0.013418547,
        0.0015703692,
        -0.0024794366,
        -0.0007107659,
        0.008691397,
        -0.006031929,
        -0.0069196066,
        0.01177866,
        0.04702908,
        0.009055023,
        -0.010445362,
        0.002238801,
        0.025054608,
        0.0037289585,
        0.001308344,
        -0.045203816,
        -0.041895527,
        -0.00416032,
        -0.0070550754,
        -0.0018662617,
        -0.009746628,
        -0.04135365,
        0.0035453625,
        0.013397156,
        -0.024683852,
        0.027293408,
        0.0077716345,
        0.033425156,
        -0.0072761034,
        0.037218284,
        0.01896564,
        -0.015842726,
        0.009746628,
        -0.0045310766,
        -0.01654146,
        -0.046430167,
        0.0023332727,
        -0.0378172,
        0.0061780927,
        0.007536346,
        0.009810797,
        0.0014215318,
        -0.0072475835,
        -0.0066664936,
        -0.019222317,
        0.017311493,
        -0.010908808,
        0.008819736,
        -0.02486923,
        -0.010473882,
        0.0039998963,
        -0.012527304,
        -0.0013431024,
        0.012477394,
        0.013582535,
        -0.021632237,
        0.010188684,
        -0.0016871219,
        0.0029749672,
        0.019122498,
        0.040868815,
        0.030573182,
        0.0137536535,
        0.0033991986,
        -0.01903694,
        0.001647016,
        -0.0029500125,
        0.003789563,
        0.038786873,
        0.024213275,
        -0.0035917072,
        -0.03545006,
        0.018110046,
        -0.012006818,
        -0.0073509677,
        -0.03818796,
        0.009803667,
        -0.012527304,
        0.013810693,
        -0.02819178,
        -0.00817804,
        -0.020519966,
        0.034794107,
        -0.04374931,
        -0.0067983973,
        -0.010167294,
        -0.0143882185,
        -0.018067267,
        0.013603925,
        0.028177522,
        0.0128695415,
        0.005447274,
        0.010573701,
        -0.009532729,
        0.007835804,
        -0.02240227,
        0.013097699,
        0.017012035,
        0.016684059,
        -0.02832012,
        0.004648721,
        0.0661088,
        0.006826917,
        -0.006630844,
        -0.0011425728,
        -0.007208369,
        0.035278942,
        -0.011350864,
        -0.011964039,
        -0.010181554,
        -0.013568276,
        -0.010459621,
        -0.014972873,
        -0.014844534,
        -0.003935727,
        0.01656998,
        0.0070515103,
        0.025425365,
        -0.0044312575,
        -0.014060241,
        -0.0069124764,
        0.0037360883,
        -0.011700231,
        -0.024256054,
        -0.004156755,
        0.029047374,
        -0.056240965,
        -0.00067511614,
        -0.0043920428,
        -0.015058433,
        0.023272123,
        -0.010067475,
        0.0006719968,
        -0.02006365,
        0.016127924,
        -0.01899416,
        -0.0046772403,
        0.00070764654,
        0.024897749,
        -0.028391419,
        0.01655572,
        0.0064419005,
        -0.02355732,
        -0.004477602,
        0.004969568,
        -0.040412497,
        -0.016883697,
        -0.00831351,
        -0.0053831046,
        -0.0008752001,
        0.006409816,
        0.00031995605,
        0.020619785,
        0.004491862,
        -0.030459102,
        0.004049806,
        0.011194006,
        0.00069516915,
        -0.0068019624,
        0.0113793835,
        -0.010046085,
        0.021118881,
        -0.004538207,
        0.028762177,
        0.0038287777,
        -0.014844534,
        -0.04608793,
        0.040726215,
        -0.0052262456,
        -0.0048055793,
        -0.0025667783,
        0.016912216,
        -0.027436009,
        -0.02237375,
        0.03162841,
        0.014901574,
        -0.026238179,
        0.0189799,
        0.037674602,
        0.026166879,
        -0.0050479975,
        -0.027920844,
        -0.030943938,
        -0.004716455,
        0.0133115975,
        -0.025083128,
        -0.005835856,
        -0.01909398,
        0.019136759,
        0.027806764,
        -0.02946091,
        -0.038159437,
        0.009247532,
        -0.04340707,
        -0.008798346,
        -0.025325546,
        0.005333195,
        0.017225934,
        0.013981812,
        0.0143882185,
        0.018680442,
        -0.022844328,
        0.03910059,
        -0.025567964,
        0.031257655,
        -0.007244019,
        -0.02245931,
        0.017311493,
        -0.00097234553,
        -0.042865198,
        -0.00072725385,
        0.019393437,
        0.012684163,
        0.0212187,
        0.040982895,
        -0.009996176,
        -0.009240402,
        -0.010645,
        0.002837716,
        -0.009161972,
        0.028077703,
        0.019892532,
        -0.046572767,
        -0.0063242563,
        0.039214667,
        0.0068910867,
        0.003989201,
        0.009297442,
        0.03405259,
        0.009133453,
        -0.01061648,
        -0.036362693,
        -0.0024134845,
        0.00054276665,
        0.014580727,
        0.026480597,
        -0.0031086537,
        -0.022288192,
        0.011015757,
        0.011493463,
        -0.046743885,
        0.01175727,
        0.0004324754,
        0.0070016007,
        0.011272435,
        0.00944004,
        -0.0035186252,
        0.004356393,
        -0.017967448,
        0.007564866,
        0.023985118,
        0.006374166,
        0.00649894,
        -0.0044241278,
        -0.04021286,
        0.0020373804,
        0.01060222,
        -0.002179979,
        0.0057324716,
        -0.0029018854,
        -0.0013992507,
        -0.0026184705,
        -0.0049766977,
        0.01537215,
        -0.00824221,
        0.0011996124,
        0.00055925467,
        0.0040569357,
        -0.033197,
        0.008905294,
        -0.021546679,
        0.00019607334,
        0.0047948845,
        0.22279635,
        -0.0063135615,
        0.0018787391,
        0.023343423,
        -0.0011702013,
        0.0066914484,
        0.018509323,
        0.019464735,
        -0.024441434,
        0.020990543,
        -0.015457709,
        0.022131333,
        -0.0026808574,
        -0.007005166,
        -0.009568379,
        -0.00234575,
        -0.05202004,
        -0.022231152,
        0.002944665,
        0.021061841,
        0.017967448,
        -0.014858794,
        -0.011728751,
        -0.0042922236,
        0.018195607,
        0.0028466284,
        0.016156442,
        0.0003861308,
        0.016028104,
        0.012634253,
        -0.023486022,
        -0.0071620243,
        -0.014858794,
        -0.00045854424,
        -0.00092510966,
        0.004381348,
        0.005447274,
        0.01420997,
        -0.0033421593,
        0.02484071,
        0.023243604,
        0.0033974163,
        0.017411312,
        -0.011008627,
        -0.007536346,
        -0.008869645,
        -0.030002786,
        -0.012270627,
        0.020662565,
        0.01903694,
        -0.027535828,
        0.019222317,
        -0.011628931,
        0.002106897,
        -0.0042102295,
        -0.0152438115,
        0.016384602,
        -0.0014054894,
        -0.01765373,
        0.0029767498,
        0.004156755,
        0.026337998,
        -0.021746317,
        0.04169589,
        -0.04591681,
        0.0039606816,
        -0.01532937,
        0.0039749416,
        -0.0077645043,
        0.007721725,
        -0.015201031,
        -0.020562746,
        -0.03938579,
        -0.009104933,
        -0.0082636,
        -0.016840918,
        -0.0021710666,
        0.038701314,
        0.025197206,
        0.01889434,
        0.007835804,
        0.04394895,
        -0.021732057,
        0.0014509427,
        0.0030926114,
        -0.014409608,
        0.005678997,
        -0.012805372,
        0.013297337,
        0.01180718,
        -0.009190492,
        -0.016869437,
        -0.028519759,
        0.0024455693,
        -0.011636062,
        -0.023970857,
        0.016812397,
        0.021147402,
        -0.017496873,
        -0.022559129,
        -0.015029913,
        0.074151374,
        0.013660965,
        -0.011928389,
        -0.031428773,
        -0.009240402,
        -0.02475515,
        0.037503485,
        0.004973133,
        -0.010901677,
        -0.006153138,
        -0.047913194,
        0.0027468093,
        -0.025682043,
        0.014580727,
        0.019536035,
        0.019949572,
        0.0021514592,
        -0.007850064,
        0.020049391,
        -0.02355732,
        -0.027008211,
        -0.010816119,
        0.0030605267,
        -0.009932006,
        -0.019179538,
        -0.022117073,
        0.008056832,
        -0.004113975,
        -0.03656233,
        0.024598291,
        0.013354377,
        -0.011315214,
        -0.0029767498,
        0.00474854,
        -0.0006185223,
        0.01184283,
        -0.010623611,
        -0.0017530739,
        0.017297234,
        -0.011586152,
        0.0050266073,
        0.014616377,
        0.0047913194,
        0.020206248,
        -0.038444635,
        0.017525392,
        0.007985532,
        -0.013390027,
        -0.011450683,
        -0.013518366,
        0.0008110306,
        -0.015086953,
        0.0047841896,
        0.0066522337,
        -0.018580623,
        -0.023300642,
        -0.026181139,
        0.029375352,
        0.021888915,
        -0.027721206,
        -0.019151019,
        0.018095788,
        0.005682562,
        -0.0104952715,
        -0.008128131,
        -0.18309686,
        0.017069075,
        0.018423764,
        -0.010402582,
        0.021831876,
        -0.0103027625,
        0.0010445361,
        -0.0019197363,
        -0.007233324,
        0.015514749,
        0.027350448,
        -0.009169103,
        -0.0008056832,
        -0.02023477,
        0.014944353,
        0.003643399,
        -0.010160164,
        0.011914129,
        0.017411312,
        0.012641383,
        0.037532,
        -0.032626603,
        0.02126148,
        -0.007450787,
        0.021660756,
        -0.015999585,
        -0.019764192,
        0.033197,
        0.00944004,
        -0.009589769,
        -0.0141671905,
        0.004007026,
        0.042722598,
        0.0034134586,
        0.008990854,
        -0.0022833631,
        0.032113247,
        -0.00822795,
        -0.007358098,
        0.039899144,
        0.022045774,
        0.036220092,
        -0.0059784544,
        -0.0021728491,
        -0.017439833,
        0.011429293,
        0.013646704,
        -0.010559441,
        -0.0068019624,
        -0.018395245,
        0.0148302745,
        -0.006823352,
        -0.010174424,
        -0.014972873,
        -0.004024851,
        0.019978091,
        0.0028181088,
        0.012698422,
        0.0011693101,
        -0.03761756,
        -0.013625314,
        -0.02716507,
        0.019293617,
        -0.012306276,
        -0.007579126,
        -0.012292016,
        -0.020691086,
        0.005429449,
        -0.034565948,
        -0.005821596,
        -0.0019696457,
        -0.0006586282,
        -0.010309893,
        0.009347351,
        0.003294032,
        0.014409608,
        -0.019678634,
        -0.02963203,
        0.017468352,
        0.009169103,
        0.0054508387,
        0.012056728,
        -0.015671607,
        0.012648513,
        0.003502583,
        -0.02954647,
        -0.01655572,
        -0.023471761,
        -0.0021710666,
        0.007700335,
        0.018181346,
        -0.0037075686,
        0.026437817,
        0.013539756,
        -0.016826658,
        0.022630429,
        0.031343214,
        0.022758767,
        0.005204856,
        -0.031143576,
        0.005361715,
        -0.0010276026,
        -0.0074080075,
        0.011472073,
        0.035963416,
        -0.008662877,
        -0.013710874,
        0.020805163,
        0.015814206,
        -0.027521567,
        -0.028633839,
        0.017468352,
        0.011051406,
        0.011521983,
        0.008484628,
        0.012128027,
        0.0059713246,
        -0.02963203,
        0.027735466,
        -0.0054686638,
        0.031428773,
        -0.022687469,
        -0.0059820195,
        0.0017985273,
        -0.0029393176,
        -0.00948282,
        -0.088126056,
        -0.033225518,
        -0.0042815288,
        0.01892286,
        -0.037360884,
        0.031229137,
        -0.0034366308,
        0.016741099,
        -0.015586048,
        0.027749725,
        -0.0037146986,
        -0.009725238,
        -0.02245931,
        0.006951691,
        0.019835493,
        0.0003486986,
        0.0053902343,
        -0.015457709,
        -0.00088856876,
        0.005326065,
        0.012042468,
        -0.038473155,
        0.017211674,
        -0.005215551,
        -0.02954647,
        -0.015457709,
        -0.027507307,
        -0.004377783,
        -0.008142391,
        0.011258175,
        0.015229551,
        -0.008940944,
        -0.0022334536,
        -0.013917643,
        0.004484732,
        -0.018024487,
        -0.03402407,
        -0.016270522,
        0.026865613,
        -0.028134743,
        0.007436527,
        0.015143992,
        0.021175921,
        -0.0013876645,
        -0.012135157,
        0.015486229,
        0.003124696,
        0.021061841,
        -0.0023760523,
        -0.012527304,
        -0.016755357,
        -0.034765586,
        -0.009233272,
        -0.014430998,
        0.029831668,
        0.018167086,
        0.0048982687,
        0.032512523,
        -0.01778207,
        -0.028149001,
        0.02589594,
        -0.0099248765,
        -0.012776852,
        -0.00824221,
        0.0128980605,
        0.00591072,
        -0.011322345,
        0.006698578,
        -0.013803563,
        -0.015942546,
        -0.025881682,
        0.005400929,
        -0.006224437,
        0.009425781,
        -0.018737482,
        -0.0018573493,
        0.003903642,
        -0.019136759,
        0.028548278,
        -0.016655538,
        0.019864012,
        -0.0066094543,
        0.009126323,
        -0.014438128,
        0.017197415,
        0.037189767,
        0.007429397,
        0.0063242563,
        -0.0010507748,
        -0.06342794,
        0.0018609143,
        0.0072226287,
        -0.012163677,
        -0.014758975,
        -0.0024277444,
        0.003190648,
        -0.01297649,
        -0.006588064,
        -0.017582431,
        -0.014930094,
        -0.03938579,
        0.013675224,
        -0.08538816,
        0.030116865,
        -0.001249522,
        -0.024213275,
        -0.0050729522,
        0.007842934,
        -0.0047806245,
        -0.028648097,
        0.010459621,
        0.006071144,
        -0.048711747,
        0.011457813,
        -0.007985532,
        -0.02123296,
        -0.008170911,
        -0.0070443805,
        0.03807388,
        -0.010445362,
        0.020762384,
        0.0027361144,
        0.002937535,
        0.03308292,
        -0.009539859,
        -0.0006301084,
        -0.02963203,
        -0.0038822521,
        -0.011386514,
        0.018737482,
        -0.0090051135,
        0.0088482555,
        0.016242003,
        -0.008092482,
        -0.0015516531,
        0.014716196,
        -0.0031549984,
        -0.014373958,
        -0.00948995,
        0.022787288,
        0.017183155,
        -0.021546679,
        -0.041524768,
        -0.028776437,
        -0.017696511,
        -0.020605525,
        -0.019450476,
        -0.012919451,
        -0.0010267113,
        0.0053688446,
        0.011550502,
        0.008705656,
        0.013839213,
        0.011914129,
        -0.029375352,
        -0.026238179,
        -0.028034924,
        -0.004994523,
        0.01899416,
        0.002401007,
        -0.013603925,
        0.003921467,
        0.059435178,
        0.017582431,
        0.0036291394,
        -0.031428773,
        0.03177101,
        -0.0044490825,
        -0.046915002,
        0.011636062,
        0.018509323,
        -0.03778868,
        -0.036961608,
        -0.006851872,
        0.008691397,
        0.025254246,
        -0.0019928182,
        -0.01541493,
        0.020363107,
        -0.00075309986,
        -0.030373544,
        0.009910616,
        0.0015801729,
        -0.01895138,
        -0.027450267,
        0.0075577362,
        0.0019785583,
        0.0039428566,
        -0.009040764,
        0.0031157837,
        -0.013939032,
        0.0054793586,
        -0.046972044,
        0.024427174,
        0.01063074,
        0.025182948,
        -0.008727046,
        0.00055524404,
        -0.0002120043,
        0.025482405,
        0.022730248,
        0.02368566,
        0.001705838,
        0.013468456,
        -0.011507723,
        -0.026295217,
        -0.005065822,
        -0.0057538613,
        -0.019935312,
        -0.02003513,
        -0.0003148314,
        0.01651294,
        0.00829925,
        -0.0128695415,
        0.00036162164,
        0.022715988,
        -0.005090777,
        -0.0034829755,
        -0.0012905191,
        -0.021418339,
        -0.035022262,
        0.01415293,
        0.0152723305,
        0.013960422,
        0.002235236,
        0.017511131,
        0.032569565,
        0.016013844,
        -0.010245724,
        -0.009974786,
        0.006841177,
        0.007329578,
        -0.002253061,
        -0.009753757,
        -0.016070884,
        -0.010987237,
        0.005055127,
        -0.0029143628,
        -0.023286384,
        -0.0054116244,
        -0.01182857,
        0.085730396,
        0.015728647,
        -0.0042030993,
        0.024056416,
        -0.009853576,
        0.029375352,
        -0.009882096,
        -0.0025168688,
        0.01658424,
        -0.017254453,
        0.013782173,
        -0.014930094,
        0.022559129,
        -0.014673416,
        -0.004841229,
        -0.01782485,
        -0.0038073878,
        0.011186875,
        -0.005586308,
        -0.021974474,
        0.011457813,
        -0.013454196,
        0.004826969,
        0.001595324,
        -0.01537215,
        0.01886582,
        0.014409608,
        -0.012598603,
        0.00064525957,
        -0.019507514,
        0.025268506,
        0.012570084,
        -0.014373958,
        -0.023343423,
        -0.01772503,
        0.0074080075,
        0.01779633,
        -0.0014295529,
        0.009896357,
        -0.008377679,
        0.018509323,
        0.0045845513,
        -0.012562954,
        -0.030516142,
        0.014602116,
        0.010730559,
        -0.011001497,
        -0.003069439,
        -0.028933296
    ]
}