{
    "doc": {
        "metadata": {
            "image": [],
            "title": "",
            "description": ""
        },
        "api": {
            "method": "get",
            "url": "",
            "auth": "required",
            "results": {
                "codes": [
                    {
                        "name": "",
                        "code": "{}",
                        "language": "json",
                        "status": 200
                    },
                    {
                        "name": "",
                        "code": "{}",
                        "language": "json",
                        "status": 400
                    }
                ]
            },
            "params": []
        },
        "next": {
            "description": "",
            "pages": []
        },
        "algolia": {
            "recordCount": 1,
            "publishPending": false,
            "updatedAt": "2023-03-08T13:52:16.254Z"
        },
        "title": "Filling Orders Explainer",
        "icon": "",
        "updates": [],
        "type": "basic",
        "slug": "filling-orders-explainer",
        "excerpt": "",
        "body": "The listing and bid acceptance APIs (`/execute/buy` and `/execute/sell`) support a few ways of requesting transaction data for filling (any combination of the below options is accepted):\n\n- pass a list of tokens, in which case the API will simply pick the best-priced orders that can get filled on those particular tokens\n- pass a list of order ids, in which case the API will use those specific order ids\n- pass a list of raw orders, in which case the API will use those specific raw orders\n\nThe first two options are self-explanatory, while the 3rd option requires the raw order data to get passed in a certain format, as follows:\n\n- each `rawOrder` object has two fields: `kind` and `data` (the `data` field will get parsed according to the `kind`)\n- both of these fields will get returned in various `orders` APIs (`/orders/asks` or `/orders/bids`): `kind` and `rawData`\n- the actual schema of each the `data` field can be found in the core SDK source code, in the `order.ts` file corresponding to each [supported exchange](https://github.com/reservoirprotocol/core/tree/main/packages/sdk/src) (the `params` field in the constructor will include it)\n\nHere's some examples:\n\n```\n[\n   {\n      \"kind\":\"looks-rare\",\n      \"data\":{\n         \"r\":\"0xfa491d0e0a13dccd6467c38c890cc90f89700b587a2e678261df70e91fef0101\",\n         \"s\":\"0x40ec4ecbcd26902a23325aee0e20364e55b94e42db1d9bf16c201b5bd5a916ab\",\n         \"v\":28,\n         \"kind\":\"single-token\",\n         \"nonce\":\"445747\",\n         \"price\":\"5800000000000000\",\n         \"amount\":\"1\",\n         \"params\":\"0x\",\n         \"signer\":\"0x9044a0bcddbd69822f6b0d0d426ff65bbef8a1bd\",\n         \"endTime\":1675948780,\n         \"tokenId\":\"281\",\n         \"currency\":\"0xc02aaa39b223fe8d0a0e5c4f27ead9083c756cc2\",\n         \"strategy\":\"0x579af6fd30bf83a5ac0d636bc619f98dbdeb930c\",\n         \"startTime\":1675941580,\n         \"collection\":\"0x63c5f88155b22e913cc46ed569edb0133aee503c\",\n         \"isOrderAsk\":true,\n         \"minPercentageToAsk\":8500\n      }\n   },\n   {\n      \"kind\":\"x2y2\",\n      \"data\":{\n         \"id\":50947214,\n         \"nft\":{\n            \"token\":\"0xeaa708c29ffce22db864385f0c6509907af45c03\",\n            \"tokenId\":\"2486\"\n         },\n         \"kind\":\"single-token\",\n         \"type\":\"sell\",\n         \"maker\":\"0x6f3339eac0deb3dbc78e628c174737046498cda4\",\n         \"price\":\"6400000000000000\",\n         \"taker\":\"0x0000000000000000000000000000000000000000\",\n         \"currency\":\"0x0000000000000000000000000000000000000000\",\n         \"deadline\":1675956570,\n         \"itemHash\":\"0xdfda59f7e3687a07b51338bd6a40d30e39c1108d1c179a7a8f9793206fc35bb2\",\n         \"royalty_fee\":50000\n      }\n   },\n   {\n      \"kind\":\"seaport\",\n      \"data\":{\n         \"kind\":\"single-token\",\n         \"salt\":\"0x360c6ebe000000000000000000000000000000000000000015b4c41d94cfd586\",\n         \"zone\":\"0x004c00500000ad104d7dbd00e3ae0a5c00560c00\",\n         \"offer\":[\n            {\n               \"token\":\"0x8f6a4d8ad2493adfd7d1540ccdba11bde5c7eb9e\",\n               \"itemType\":2,\n               \"endAmount\":\"1\",\n               \"startAmount\":\"1\",\n               \"identifierOrCriteria\":\"3577\"\n            }\n         ],\n         \"counter\":\"0\",\n         \"endTime\":1691493881,\n         \"offerer\":\"0xbb93664780e5e4e22f5255c774bfc455ebfa789e\",\n         \"zoneHash\":\"0x0000000000000000000000000000000000000000000000000000000000000000\",\n         \"orderType\":2,\n         \"signature\":\"0xb3277794bf3f113dfbaaa9e4691883a0a7c51cdea56840e906b16c0eb62c052b5a36203276d55d7279397c9a9762638ad369cd2b241da6a7babe8109ceac7979\",\n         \"startTime\":1675941882,\n         \"conduitKey\":\"0x0000007b02230091a7ed01230072f7006a004d60a8d4e71d599b8104250f0000\",\n         \"consideration\":[\n            {\n               \"token\":\"0x0000000000000000000000000000000000000000\",\n               \"itemType\":0,\n               \"endAmount\":\"73075000000000000\",\n               \"recipient\":\"0xbb93664780e5e4e22f5255c774bfc455ebfa789e\",\n               \"startAmount\":\"73075000000000000\",\n               \"identifierOrCriteria\":\"0\"\n            },\n            {\n               \"token\":\"0x0000000000000000000000000000000000000000\",\n               \"itemType\":0,\n               \"endAmount\":\"1975000000000000\",\n               \"recipient\":\"0x0000a26b00c1f0df003000390027140000faa719\",\n               \"startAmount\":\"1975000000000000\",\n               \"identifierOrCriteria\":\"0\"\n            },\n            {\n               \"token\":\"0x0000000000000000000000000000000000000000\",\n               \"itemType\":0,\n               \"endAmount\":\"3950000000000000\",\n               \"recipient\":\"0x5b5173599a2f29973397c34d01a49b3a0ee8963d\",\n               \"startAmount\":\"3950000000000000\",\n               \"identifierOrCriteria\":\"0\"\n            }\n         ]\n      }\n   },\n   {\n      \"kind\":\"nftx\",\n      \"data\":{\n         \"path\":[\n            \"0xc02aaa39b223fe8d0a0e5c4f27ead9083c756cc2\",\n            \"0x227c7df69d3ed1ae7574a1a7685fded90292eb48\"\n         ],\n         \"pool\":\"0x227c7df69d3ed1ae7574a1a7685fded90292eb48\",\n         \"extra\":{\n            \"prices\":[\n               \"1260108297127984902\",\n               \"1276394899256615323\",\n               \"1292999305888243388\",\n               \"1309929839687630165\",\n               \"1327195097557417461\",\n               \"1344803961553668927\",\n               \"1362765610311681745\",\n               \"1381089531009513537\",\n               \"1399785531898341045\",\n               \"1418863755430552809\"\n            ]\n         },\n         \"price\":\"1260108297127984902\",\n         \"amount\":\"1\",\n         \"amounts\":[\n            \n         ],\n         \"vaultId\":\"392\",\n         \"currency\":\"0xc02aaa39b223fe8d0a0e5c4f27ead9083c756cc2\",\n         \"collection\":\"0x5af0d9827e0c53e4799bb226655a1de152a425a5\",\n         \"specificIds\":[\n            \"70\"\n         ]\n      }\n   },\n   {\n      \"kind\":\"sudoswap\",\n      \"data\":{\n         \"pair\":\"0x44d2193a0f966245baa6cb9576d7b675adb5956b\",\n         \"extra\":{\n            \"prices\":[\n               \"1213109641829303257\"\n            ]\n         }\n      }\n   }\n]\n```",
        "order": 14,
        "isReference": false,
        "deprecated": false,
        "hidden": false,
        "sync_unique": "",
        "link_url": "",
        "link_external": false,
        "previousSlug": "",
        "slugUpdatedAt": "2023-03-08T05:36:22.426Z",
        "revision": 2,
        "_id": "6408930f166573083f5c2be5",
        "user": "62a2345635a16d0608ba84f4",
        "project": "62a239ec3e4c0800663c6d05",
        "category": "63f3e45464c04e0012a8fb20",
        "createdAt": "2023-03-08T13:52:15.682Z",
        "updatedAt": "2023-03-08T13:52:15.682Z",
        "version": "63f3e45464c04e0012a8fc52",
        "__v": 0,
        "parentDoc": null,
        "isApi": false,
        "id": "6408930f166573083f5c2be5"
    },
    "meta": {
        "slug": "filling-orders-explainer",
        "type": "docs",
        "parent": null,
        "image": [],
        "title": "Filling Orders Explainer",
        "title_raw": "Filling Orders Explainer",
        "description": "The listing and bid acceptance APIs (/execute/buy and /execute/sell) support a few ways of requesting transaction data for filling (any combination of the below options is accepted): pass a list of tokens, in which case the API will simply pick the best-priced orders that can get filled on those par...",
        "_id": "6408930f166573083f5c2be5",
        "hidden": false
    },
    "activeDoc": "filling-orders-explainer",
    "embedding": [
        -0.013129257,
        0.01015871,
        -0.011917218,
        0.008498287,
        -0.08194226,
        0.011545899,
        -0.027113248,
        -0.028234208,
        -0.01857993,
        -0.035646565,
        0.030181877,
        0.00041466803,
        -0.005944597,
        -0.030518167,
        0.010410926,
        0.012884047,
        0.012940095,
        -0.011034461,
        0.016338008,
        -0.014712615,
        0.00094055646,
        0.012344584,
        -0.020611672,
        0.0062108254,
        -0.017627114,
        0.0058605247,
        0.0007689093,
        -0.00807092,
        -0.02031742,
        -0.02908894,
        0.018621966,
        -0.0007925545,
        -0.03926166,
        -0.006021663,
        -0.009752362,
        -0.006855378,
        -0.011188593,
        0.001585109,
        -0.0055207335,
        0.0054822005,
        -0.0007960575,
        -0.004010939,
        0.00012359035,
        -0.0025414291,
        -0.008946671,
        0.01015871,
        0.0077836737,
        0.010277812,
        -0.0041020173,
        0.0065576225,
        0.009317989,
        0.014992855,
        -0.04932229,
        -0.011258653,
        0.0052474993,
        0.0023767878,
        0.019350592,
        0.03012583,
        -0.0012593297,
        -0.009149845,
        0.02475923,
        -0.002485381,
        -0.02156449,
        0.008638406,
        0.02059766,
        -0.006060196,
        -0.0047815996,
        -0.00263601,
        0.0045328867,
        -0.037580222,
        -0.0011761334,
        -0.005902561,
        -0.0053035473,
        0.012624824,
        0.05338577,
        -0.010768233,
        -0.008014872,
        0.016085792,
        0.009219905,
        -0.02428282,
        0.007016516,
        -0.0006042681,
        -0.005051331,
        0.051087804,
        0.011062485,
        0.04043867,
        0.017248789,
        0.03923364,
        0.0027183308,
        -0.005205463,
        0.03889735,
        -0.002932014,
        0.0073072654,
        0.003996927,
        -0.016884476,
        0.013591654,
        -0.0056783687,
        0.036627404,
        -0.01745897,
        -0.004953247,
        -0.0037552197,
        0.030378046,
        -0.030350022,
        -0.016127829,
        -0.048061207,
        -0.004963756,
        0.011034461,
        0.0028391844,
        0.0067923237,
        -0.0005806228,
        -0.015006867,
        0.041139275,
        -0.011749074,
        -0.043157004,
        0.00693945,
        0.001719099,
        0.02372234,
        -0.03609495,
        -0.036515307,
        -0.023876471,
        0.017725198,
        0.013871894,
        0.034973986,
        -0.028276244,
        0.010775239,
        0.0007146127,
        -0.01600172,
        -0.03547842,
        0.0032052482,
        0.0025256656,
        0.041979995,
        0.030798407,
        0.0045679165,
        0.0005814986,
        -0.002865457,
        0.011594942,
        -0.013409497,
        -0.0023627758,
        -0.011412785,
        -0.027701752,
        0.017332861,
        0.02324593,
        0.0082040345,
        -0.00071154756,
        -0.019392628,
        -0.009332001,
        0.031470984,
        -0.0067152577,
        0.0016928264,
        -0.03575866,
        0.018720051,
        -0.011784104,
        -0.010200746,
        0.007804692,
        -0.00069928705,
        -0.03306835,
        -0.00093880494,
        0.007293253,
        0.031751223,
        -0.010081644,
        0.011216617,
        0.012519735,
        -0.010964401,
        -0.015385191,
        0.0074894214,
        0.02191479,
        0.03026595,
        -0.0063369335,
        -0.0018793613,
        -0.02470318,
        -0.021550478,
        -0.016015733,
        -0.003581821,
        0.022223054,
        -0.011749074,
        0.029481277,
        0.021858742,
        0.002359273,
        -0.03214356,
        0.01415914,
        0.021298261,
        0.002443345,
        0.022152994,
        0.03937376,
        0.0038708188,
        -0.014446386,
        -0.0037762378,
        -0.03959795,
        0.003954891,
        0.016197888,
        -0.0010631615,
        0.017627114,
        0.0022156497,
        -0.008119962,
        -0.5779675,
        -0.06142867,
        -0.0017620107,
        -0.022797547,
        0.015847588,
        0.004690522,
        0.009247929,
        0.030686311,
        -0.0010789251,
        0.0145304585,
        0.0028602025,
        0.03598285,
        -0.016856452,
        -0.023091799,
        -0.0056048054,
        -0.0018163073,
        0.018523883,
        -0.018467834,
        0.018341726,
        -0.009822422,
        -0.0032753083,
        0.019252507,
        0.006844869,
        0.00052720204,
        0.018215619,
        0.009205894,
        -0.01193123,
        -0.0010517768,
        0.022363175,
        -0.01147584,
        -0.023273956,
        0.025627974,
        0.02003718,
        -0.00048691747,
        0.04974265,
        0.0046484857,
        -0.019981133,
        0.015987707,
        0.031078648,
        0.041419514,
        -0.012015302,
        0.0048306417,
        0.025894202,
        -0.010046614,
        0.025908213,
        -0.008911641,
        0.030013734,
        -0.00028812204,
        -0.011503863,
        -0.0107612265,
        -0.008946671,
        -0.000611712,
        -0.0067818146,
        -0.0048026177,
        0.026328575,
        -0.018762087,
        0.023330003,
        -0.01440435,
        0.017753221,
        -0.011293683,
        0.016183876,
        0.006130256,
        -0.03458165,
        -0.037047766,
        -0.009969548,
        0.022152994,
        0.0006226589,
        -0.0045714197,
        -0.017346874,
        -0.03528225,
        0.0004969886,
        0.046519887,
        0.02212497,
        -0.0002688555,
        -0.0039654,
        0.02073778,
        0.039429806,
        0.0064910655,
        -0.006084717,
        0.022293115,
        0.020065203,
        -0.022713475,
        -0.017823283,
        -0.027449535,
        0.024535036,
        0.035674587,
        -0.01273692,
        -0.029901639,
        0.03236775,
        0.008981701,
        0.0076295417,
        0.023344016,
        -0.000040640312,
        -0.01989706,
        0.0038322858,
        0.038729206,
        -0.002942523,
        -0.0014651312,
        0.005152918,
        -0.031162718,
        -0.0010815524,
        0.006900917,
        -0.020149276,
        0.018790111,
        0.034189314,
        0.01366872,
        -0.0037762378,
        0.0067327726,
        0.010656137,
        -0.026748935,
        -0.0015667183,
        0.009724338,
        -0.037468124,
        -0.031106671,
        -0.014852735,
        -0.023161858,
        0.027463548,
        0.011230629,
        0.038841303,
        -0.01489477,
        0.027435523,
        0.010873323,
        0.046043478,
        0.0034049193,
        0.025445817,
        -0.01822963,
        -0.008960683,
        -0.003037104,
        0.01089434,
        0.0011945242,
        -0.013388479,
        -0.017136693,
        0.03124679,
        -0.020219335,
        0.000119868404,
        -0.0038462977,
        0.019112388,
        0.006021663,
        0.021158142,
        -0.0137037495,
        -0.0071811574,
        -0.0036115965,
        0.023077788,
        -0.022573354,
        -0.007398343,
        -0.0059375907,
        -0.024478989,
        0.0071426244,
        -0.017206753,
        -0.012877041,
        -0.008133974,
        -0.022503294,
        0.00092742016,
        0.011629972,
        -0.0076155295,
        0.0029057413,
        -0.012379615,
        -0.017515017,
        -0.007902776,
        0.00290399,
        -0.008687449,
        0.010866317,
        0.0072862473,
        -0.011181587,
        -0.010628113,
        -0.036739502,
        0.012379615,
        0.0013775561,
        -0.008834574,
        -0.047612824,
        0.005016301,
        -0.0037342017,
        -0.015259083,
        0.0021000507,
        -0.0018758584,
        0.014642554,
        -0.02212497,
        0.0041405503,
        0.00873649,
        0.0065856464,
        -0.0027568638,
        0.017977415,
        -0.02581013,
        0.012505722,
        0.03318045,
        0.01675837,
        0.009346013,
        0.006837863,
        -0.014068062,
        0.03304033,
        -0.0074193613,
        0.03026595,
        0.0009212899,
        0.019742928,
        -0.004900702,
        0.017557053,
        0.02978954,
        -0.017066633,
        0.0031124186,
        -0.009044755,
        -0.006806336,
        -0.004827139,
        -0.017627114,
        -0.002024736,
        0.03152703,
        -0.012435663,
        -0.0003603715,
        -0.038168725,
        0.033152424,
        0.015483275,
        0.019939097,
        -0.019000292,
        -0.0039759087,
        0.01649214,
        0.0033190958,
        0.017711185,
        0.02400258,
        -0.0018198104,
        -0.017697174,
        -0.015553336,
        0.0043962696,
        -0.03228368,
        0.035730634,
        -0.015693456,
        -0.003480234,
        0.013605665,
        0.0051599243,
        -0.005930585,
        -0.0100886505,
        -0.003375144,
        0.021158142,
        0.008554335,
        0.00037219413,
        -0.012778956,
        0.011987278,
        0.00058938033,
        0.018720051,
        -0.0058710338,
        0.02031742,
        -0.026748935,
        0.0076085236,
        0.024016593,
        0.0131082395,
        -0.032760087,
        0.034497578,
        -0.0054962123,
        0.0044838446,
        0.046519887,
        -0.020849876,
        -0.024450965,
        -0.0033173442,
        -0.008904635,
        -0.0071811574,
        -0.012729915,
        0.010915359,
        -0.025347734,
        0.029873613,
        0.005748429,
        0.024997434,
        0.014572495,
        0.0077626556,
        -0.014992855,
        0.030658286,
        -0.00796583,
        0.0022314133,
        0.0064104963,
        -0.015903635,
        0.0034714765,
        -0.0015964939,
        0.0052965414,
        0.024394916,
        -0.015805552,
        -0.05128397,
        0.0016499147,
        0.044193894,
        0.0016481632,
        -0.006154777,
        0.016800405,
        0.0072301994,
        -0.007090079,
        -0.030293975,
        0.0020089725,
        0.035506442,
        0.019126398,
        -0.0036115965,
        -0.031947393,
        -0.008575353,
        0.01898628,
        -0.0073072654,
        0.008925653,
        -0.008764515,
        -0.007058552,
        -0.0018460829,
        -0.00015030074,
        -0.005846513,
        0.007818704,
        0.035730634,
        -0.002422327,
        0.008652419,
        -0.0028076572,
        0.013577642,
        0.0014432374,
        -0.017248789,
        -0.018271666,
        0.06025166,
        0.012940095,
        -0.016590225,
        -0.021606525,
        0.004963756,
        -0.009731344,
        -0.010873323,
        0.012870035,
        -0.030658286,
        -0.009156851,
        0.015945671,
        -0.021676585,
        -0.028556485,
        0.00821104,
        0.025333721,
        -0.009044755,
        0.015118963,
        -0.016436093,
        -0.016898489,
        0.028836725,
        0.004088005,
        0.053525895,
        -0.008890623,
        0.011657996,
        -0.0112236235,
        -0.023217907,
        -0.018075498,
        0.014628543,
        -0.005138906,
        0.01968688,
        -0.012085362,
        -0.022503294,
        0.005892052,
        0.024086652,
        0.011384761,
        0.001106949,
        -0.033853024,
        -0.02156449,
        0.021648562,
        -0.013794828,
        0.0012847265,
        -0.020359457,
        -0.0020755297,
        0.020303408,
        0.03374093,
        0.014215188,
        0.016239924,
        0.0055977996,
        0.0052299844,
        -0.01193123,
        -0.02838834,
        -0.02691708,
        0.01928053,
        0.027351452,
        -0.013934948,
        0.052292835,
        0.033656858,
        0.008161998,
        0.0013723016,
        0.010628113,
        0.008778526,
        -0.0005223854,
        0.0079308,
        0.0010325103,
        0.018341726,
        -0.022433234,
        -0.016842442,
        0.0056643565,
        0.03416129,
        0.0014029529,
        -0.016996574,
        -0.008729485,
        -0.04696827,
        -0.016408069,
        0.015259083,
        -0.013220335,
        -0.0043647424,
        -0.0028146633,
        -0.0027568638,
        -0.03233973,
        0.0023470123,
        -0.015020879,
        -0.0074964273,
        0.005002289,
        -0.008456251,
        -0.020149276,
        -0.040802985,
        0.006428011,
        -0.03735603,
        0.00481663,
        -0.009556194,
        0.017024597,
        -0.0018373253,
        -0.0015203035,
        0.0065786405,
        0.0045749224,
        0.022110958,
        0.009353019,
        0.026482707,
        0.00097471074,
        -0.010284819,
        -0.03354476,
        -0.020345444,
        -0.01040392,
        -0.013675726,
        0.0020369964,
        0.01600172,
        -0.007349301,
        0.014950819,
        0.021172153,
        -0.025754081,
        -0.009514158,
        -0.0015816061,
        0.008939665,
        0.0071426244,
        0.0034609674,
        0.012442668,
        0.030237926,
        -0.003529276,
        -0.00481663,
        0.021130117,
        -0.0071706483,
        -0.011041467,
        -0.019855024,
        -0.010901347,
        -0.008042896,
        0.02066772,
        -0.012961113,
        -0.008603376,
        0.0013880652,
        -0.012842011,
        -0.03735603,
        0.009542181,
        0.014138122,
        -0.0066241794,
        -0.012870035,
        -0.023035752,
        0.001553582,
        -0.025670009,
        0.0012067847,
        -0.011174581,
        -0.011174581,
        0.016562201,
        -0.026426658,
        -0.026664862,
        0.0008035014,
        0.0030878976,
        -0.027393488,
        0.00071198546,
        0.012050332,
        -0.006855378,
        0.01614184,
        0.0014677584,
        -0.0075104395,
        -0.004970762,
        0.010011584,
        -0.015903635,
        0.020345444,
        -0.027421512,
        0.021676585,
        -0.0046870187,
        -0.016716333,
        -0.015371179,
        -0.02470318,
        0.008575353,
        -0.034189314,
        -0.01040392,
        -0.0036396207,
        -0.03354476,
        0.030462118,
        -0.020121252,
        -0.00386031,
        -0.01186117,
        -0.014040038,
        -0.018776098,
        -0.0015763516,
        -0.0018933734,
        -0.016926512,
        0.041139275,
        0.04063484,
        0.009051761,
        0.02872463,
        0.0034399494,
        0.009787392,
        -0.010838293,
        0.004329712,
        0.015076927,
        0.0064945687,
        -0.016085792,
        -0.013479558,
        0.006081214,
        0.00786074,
        -0.0043577366,
        -0.0013994499,
        0.009675296,
        0.022251079,
        0.007272235,
        0.006932444,
        -0.017991425,
        -0.023021739,
        -0.00034395116,
        0.0037271958,
        0.008358167,
        0.005079355,
        -0.027043186,
        -0.0053525893,
        0.022110958,
        0.0077836737,
        0.014936807,
        -0.0025782106,
        0.023428088,
        -0.0057939677,
        0.028276244,
        -0.008281101,
        -0.009934518,
        0.011412785,
        -0.0028181663,
        -0.008953677,
        -0.03668345,
        0.0024135695,
        -0.0062563643,
        0.030854454,
        -0.0014029529,
        -0.004953247,
        -0.0087224785,
        -0.016394056,
        0.0048796837,
        -0.007818704,
        0.012870035,
        -0.01489477,
        -0.022671439,
        -0.011559912,
        -0.011027455,
        0.015118963,
        -0.010445956,
        0.004003933,
        0.042820714,
        0.0063929814,
        -0.02908894,
        -0.012708897,
        -0.010838293,
        0.0006519965,
        0.024493,
        0.016884476,
        0.01565142,
        -0.0032017452,
        0.008687449,
        -0.016239924,
        -0.036263093,
        -0.023694316,
        -0.0009177869,
        0.020527601,
        0.03144296,
        -0.0008818811,
        -0.04696827,
        0.02072377,
        -0.0065366044,
        -0.020065203,
        -0.03539435,
        0.023512159,
        -0.0049567497,
        0.0022664433,
        -0.004116029,
        0.0105300285,
        -0.027813848,
        0.020261372,
        -0.024521025,
        0.0046660006,
        0.018776098,
        -0.0023242428,
        -0.029060917,
        0.024226772,
        0.008372178,
        0.019855024,
        0.005765944,
        0.002010724,
        -0.00003754782,
        0.00078730006,
        -0.023063775,
        0.017767234,
        0.024450965,
        0.000111165624,
        -0.014740638,
        0.00063360576,
        0.059242796,
        0.012064344,
        0.010095656,
        0.010396915,
        0.028206185,
        0.029229062,
        -0.0011411033,
        -0.016113816,
        0.022461258,
        -0.018187594,
        -0.011496858,
        -0.005215972,
        -0.015006867,
        -0.015399204,
        -0.0324238,
        -0.013080215,
        0.03715986,
        -0.014446386,
        0.004329712,
        -0.04772492,
        -0.006004148,
        -0.029677445,
        -0.017024597,
        0.01089434,
        0.045342878,
        -0.010081644,
        -0.013857882,
        0.011384761,
        0.01857993,
        0.02254533,
        0.018327715,
        0.0045574075,
        0.016309984,
        0.028920798,
        -0.007804692,
        0.0045539048,
        -0.027925944,
        0.030770382,
        -0.030658286,
        -0.019826999,
        0.0056678597,
        -0.020681733,
        -0.012884047,
        -0.013724768,
        -0.046547912,
        0.014810699,
        0.009402062,
        -0.008890623,
        -0.025487853,
        0.025684021,
        0.022363175,
        0.023974556,
        -0.0030633765,
        -0.025221625,
        -0.016057769,
        -0.01593166,
        0.001747123,
        -0.012512729,
        0.020751793,
        -0.01928053,
        0.003086146,
        -0.01600172,
        0.02547384,
        0.006291394,
        0.0024801265,
        -0.009857452,
        0.03595483,
        -0.0009755865,
        -0.0024871326,
        0.005016301,
        0.0065646283,
        -0.0035940816,
        -0.0061407653,
        0.044670302,
        0.036066923,
        0.0075594815,
        0.018481847,
        0.02831828,
        0.046660006,
        0.027659716,
        -0.03200344,
        -0.036627404,
        -0.020233348,
        -0.0006979735,
        -0.005331571,
        -0.020009156,
        -0.02198485,
        0.029593373,
        -0.00058543944,
        -0.02978954,
        -0.04097113,
        0.010614101,
        -0.032647993,
        0.018075498,
        -0.017907353,
        0.019560771,
        0.0076015177,
        0.008652419,
        -0.0004759706,
        0.045482997,
        -0.039121542,
        0.010137692,
        -0.0633343,
        0.0142432125,
        0.025025457,
        -0.012673867,
        0.02956535,
        -0.00076321687,
        -0.035506442,
        0.003469725,
        0.02761768,
        0.01328339,
        0.012449674,
        0.022587366,
        -0.014712615,
        -0.0024013089,
        0.0033050838,
        0.016646273,
        -0.022110958,
        -0.0056853746,
        0.0021315776,
        -0.041979995,
        0.00095807144,
        0.0014055802,
        -0.010936377,
        -0.0014327285,
        0.016842442,
        0.0021946316,
        -0.0044943537,
        -0.029901639,
        -0.019364603,
        -0.011258653,
        -0.014117104,
        -0.0025186595,
        0.01193123,
        -0.0009020234,
        -0.010207752,
        0.01773921,
        -0.0055312426,
        -0.015245072,
        0.027715763,
        0.018383762,
        0.020961974,
        -0.013892912,
        -0.0022156497,
        0.008169004,
        0.0084912805,
        0.0046554916,
        0.007888764,
        0.004729055,
        0.014502434,
        -0.017486993,
        0.018888194,
        -0.033572786,
        0.00051537936,
        0.0046204617,
        -0.022293115,
        0.0015132976,
        0.02510953,
        0.0031684667,
        -0.009374037,
        -0.004182586,
        -0.010011584,
        -0.020121252,
        0.015595372,
        -0.01886017,
        -0.009030743,
        -0.038953397,
        -0.0023312487,
        -0.019714903,
        -0.019728916,
        -0.021102093,
        0.21634549,
        -0.008547328,
        -0.011202605,
        0.02691708,
        -0.00006688547,
        0.001223424,
        0.00042517704,
        -0.0043472275,
        -0.012442668,
        0.003888334,
        -0.0035310276,
        0.020975985,
        -0.01489477,
        -0.008498287,
        0.015287107,
        -0.0056783687,
        -0.049210194,
        -0.022082934,
        -0.0003476731,
        -0.001975694,
        0.006084717,
        0.0027411003,
        -0.008680442,
        -0.015679443,
        0.010081644,
        0.0012873538,
        0.019658856,
        0.011770092,
        0.00584301,
        0.022138983,
        -0.0106070945,
        0.009451103,
        -0.0045398925,
        0.006886905,
        -0.018972266,
        0.0055172304,
        -0.007195169,
        0.004091508,
        0.02037347,
        0.0112236235,
        0.01919646,
        0.002907493,
        -0.0036956687,
        0.011805122,
        -0.01787933,
        0.014418363,
        -0.016842442,
        -0.018173583,
        0.018187594,
        0.00949314,
        -0.03284416,
        0.0008551707,
        0.017991425,
        0.0037412078,
        -0.004834145,
        0.007216187,
        0.023960544,
        0.033656858,
        -0.003993424,
        0.005163427,
        -0.027589656,
        0.025025457,
        0.0058780396,
        0.027365463,
        -0.010249788,
        -0.008603376,
        -0.0288087,
        -0.021606525,
        0.015749503,
        0.020961974,
        -0.006806336,
        -0.014341297,
        -0.013010155,
        -0.0005828122,
        -0.030378046,
        -0.015749503,
        0.02978954,
        0.004998786,
        0.014362315,
        0.012043326,
        0.023147848,
        0.012680872,
        0.009296971,
        -0.0029372685,
        0.01787933,
        -0.009346013,
        -0.0026710401,
        -0.01747298,
        0.004242137,
        0.004073993,
        -0.017837293,
        -0.020891912,
        -0.015525311,
        0.009353019,
        -0.0035467912,
        -0.0076785837,
        0.019126398,
        -0.0002885599,
        -0.029173013,
        -0.02763169,
        -0.03351674,
        0.05077954,
        0.008554335,
        -0.0058605247,
        -0.029201036,
        -0.025824143,
        -0.023428088,
        0.0115108695,
        0.0016341511,
        -0.013374467,
        0.006039178,
        -0.047472704,
        -0.002091293,
        -0.014726627,
        0.0028426873,
        0.003532779,
        -0.008091938,
        -0.0007111097,
        0.0070935823,
        -0.0053035473,
        -0.027869895,
        -0.056664586,
        -0.0054051345,
        0.007146127,
        0.014292254,
        -0.012064344,
        -0.041279394,
        0.004109023,
        0.01642208,
        -0.043016884,
        0.027379476,
        0.014992855,
        -0.014698602,
        -0.023554195,
        -0.017080644,
        -0.012757938,
        0.007902776,
        0.0056083086,
        0.0004632722,
        -0.003919861,
        -0.008687449,
        0.029285109,
        -0.005846513,
        0.02656678,
        0.021326285,
        -0.0073633133,
        -0.004133544,
        0.0057414225,
        -0.014922795,
        -0.018061485,
        -0.013787822,
        -0.016562201,
        0.032619968,
        -0.014432374,
        0.017669149,
        -0.0032858173,
        0.001518552,
        0.0127999745,
        0.007769662,
        0.023414075,
        -0.049378335,
        -0.018341726,
        -0.012624824,
        0.002928511,
        -0.010130686,
        -0.021382334,
        -0.17733605,
        0.040018313,
        0.025936238,
        -0.013332431,
        0.0055802846,
        0.016197888,
        0.011391767,
        0.00095632,
        -0.0010929371,
        -0.0036606386,
        0.03166715,
        -0.024661144,
        -0.02135431,
        -0.011132545,
        0.0074824155,
        -0.0017094658,
        -0.011111527,
        0.008925653,
        0.032816138,
        0.02984559,
        0.026734922,
        -0.018341726,
        0.016716333,
        0.004795612,
        -0.0117420675,
        -0.0057834587,
        -0.01663226,
        0.01270189,
        -0.017360885,
        -0.00509687,
        0.001261957,
        0.004080999,
        0.014670579,
        0.006049687,
        -0.004757079,
        0.00016234232,
        0.016408069,
        -0.008918647,
        -0.008862599,
        0.036851596,
        0.002073778,
        -0.008274094,
        -0.020919938,
        0.0110694915,
        0.019042326,
        -0.018075498,
        0.011777097,
        -0.012778956,
        -0.014712615,
        -0.028122112,
        0.043633413,
        -0.03354476,
        -0.032115538,
        0.011496858,
        -0.003012583,
        0.015175011,
        0.0053140563,
        -0.0061898073,
        -0.011188593,
        -0.01738891,
        0.0064735506,
        -0.01975694,
        0.0047220485,
        -0.032647993,
        0.0017147202,
        0.01182614,
        -0.014488422,
        0.018425798,
        -0.051928524,
        0.0009484382,
        -0.013556624,
        0.005993639,
        0.021130117,
        0.008582358,
        0.007216187,
        0.016043756,
        -0.0027043186,
        -0.005906064,
        -0.00049304776,
        0.016155852,
        -0.032872185,
        0.036739502,
        -0.023680303,
        0.026258513,
        0.006070705,
        0.0024153208,
        -0.0020299905,
        -0.013654708,
        -0.0064139995,
        -0.0104529625,
        -0.014110098,
        -0.0072862473,
        0.0009335504,
        -0.0036045907,
        -0.0064840596,
        0.021410357,
        0.01440435,
        0.0032350237,
        0.005930585,
        -0.013325425,
        0.011307695,
        -0.012624824,
        -0.0051424094,
        0.01377381,
        0.023147848,
        0.009093797,
        -0.005885046,
        0.017164716,
        0.038000584,
        -0.033656858,
        -0.03598285,
        0.02254533,
        0.00042408236,
        0.019378616,
        0.021718621,
        0.033236496,
        -0.013920936,
        -0.009275953,
        0.029957686,
        -0.025431806,
        0.043381196,
        -0.01207135,
        -0.017627114,
        0.020135265,
        0.006221334,
        -0.01440435,
        -0.0880515,
        -0.041419514,
        0.010852305,
        0.020709757,
        -0.030237926,
        0.015455252,
        -0.0122044645,
        0.01759909,
        -0.0024976416,
        0.04214814,
        -0.036487285,
        -0.007839722,
        -0.0007724123,
        0.0037306987,
        0.03833687,
        0.029397205,
        -0.004168574,
        0.004031957,
        -0.013248359,
        0.032255657,
        -0.01822963,
        -0.011216617,
        -0.002509902,
        -0.016716333,
        -0.012421651,
        -0.00835116,
        -0.040382624,
        0.0067432816,
        0.024941385,
        0.027365463,
        0.0005258884,
        -0.016548188,
        0.010312842,
        -0.01815957,
        0.009535176,
        0.013129257,
        -0.0135496175,
        -0.022040898,
        0.0131853055,
        -0.025081504,
        0.010712185,
        0.016548188,
        0.020527601,
        -0.00072862476,
        0.003002074,
        -0.0017655138,
        -0.019434663,
        0.01628196,
        -0.0003686911,
        -0.002907493,
        -0.044193894,
        -0.01780927,
        -0.016478129,
        -0.010424938,
        0.03402117,
        0.02037347,
        0.001490528,
        0.005965615,
        0.003026595,
        -0.019028315,
        0.021858742,
        -0.0074613974,
        -0.018187594,
        0.00873649,
        -0.001237436,
        0.02003718,
        -0.039317712,
        -0.011027455,
        0.011763086,
        -0.0054681883,
        -0.015889624,
        0.041643705,
        -0.00052851567,
        0.012968119,
        -0.009850446,
        0.008953677,
        -0.01738891,
        0.0026202467,
        0.020821853,
        -0.012421651,
        0.006967474,
        -0.012372608,
        -0.009801404,
        0.011286677,
        0.027477559,
        0.012631831,
        0.011055479,
        -0.009528169,
        0.017360885,
        -0.06058795,
        0.008554335,
        0.0077556497,
        -0.004084502,
        -0.020331433,
        -0.021466406,
        0.004778097,
        -0.014376326,
        0.008729485,
        -0.015273095,
        -0.017627114,
        -0.036431238,
        0.031078648,
        -0.055992007,
        0.03542237,
        0.008190022,
        -0.009233917,
        0.00026206844,
        -0.0051879482,
        0.010908353,
        -0.019182447,
        0.0058885487,
        0.01745897,
        -0.02616043,
        -0.0055662724,
        -0.018173583,
        -0.030658286,
        -0.016562201,
        -0.026468694,
        0.02393252,
        -0.028290257,
        0.043997724,
        0.01898628,
        0.025445817,
        -0.012617819,
        0.0053245653,
        -0.0133954855,
        -0.019084362,
        0.01857993,
        -0.015497288,
        0.018734062,
        -0.009941524,
        0.007818704,
        0.023189884,
        0.0075945114,
        -0.002457357,
        0.03701974,
        0.0024170724,
        -0.018467834,
        -0.017066633,
        0.021690598,
        0.033712905,
        -0.0089326585,
        -0.011833146,
        -0.027743788,
        -0.015973696,
        -0.010908353,
        -0.021214189,
        -0.030714335,
        0.0020755297,
        0.027421512,
        0.008792539,
        0.006778312,
        0.011735062,
        0.016842442,
        -0.035114106,
        -0.031499006,
        -0.026202466,
        -0.016828429,
        0.021718621,
        0.00019978067,
        -0.005867531,
        0.017360885,
        0.07095684,
        -0.0075524757,
        0.00011472336,
        -0.017991425,
        0.03326452,
        -0.022307126,
        -0.03839292,
        0.009072779,
        0.01933658,
        -0.016688308,
        -0.012961113,
        -0.009654278,
        -0.028276244,
        0.005885046,
        0.012120392,
        0.010214758,
        0.014922795,
        0.0081269685,
        -0.004137047,
        0.025922226,
        0.012477699,
        0.012456681,
        -0.02984559,
        0.00065637525,
        0.0027796333,
        -0.012610813,
        -0.0004899826,
        0.0044032754,
        -0.02045754,
        0.008596371,
        -0.03819675,
        0.0151469875,
        -0.015805552,
        0.03867316,
        0.029761517,
        0.010326854,
        0.0005149415,
        0.011784104,
        0.045819286,
        0.005958609,
        -0.0004777221,
        -0.008337148,
        -0.0053806133,
        -0.011959254,
        -0.020541612,
        -0.019000292,
        -0.041783825,
        -0.027463548,
        -0.009240923,
        0.014572495,
        -0.007874751,
        -0.022629403,
        -0.013815845,
        0.013955966,
        -0.02149443,
        0.015987707,
        0.023330003,
        -0.025515877,
        -0.023694316,
        0.02386246,
        0.0020054695,
        0.016716333,
        0.0045188745,
        -0.0009869712,
        0.023049762,
        0.004165071,
        0.013066203,
        0.0024205754,
        0.01328339,
        0.009997572,
        -0.0042281253,
        -0.0023487639,
        -0.020429516,
        -0.012085362,
        -0.019014303,
        -0.030658286,
        -0.024563061,
        -0.003483737,
        0.0043262094,
        0.083791845,
        0.014628543,
        0.029201036,
        0.01794939,
        -0.02296569,
        0.03505806,
        -0.014173152,
        0.008119962,
        0.008547328,
        -0.019014303,
        0.0118962,
        -0.022237066,
        -0.00038467356,
        -0.032788113,
        0.0017383655,
        -0.0023435093,
        0.0057729497,
        0.0064420234,
        0.00072424597,
        -0.0001726324,
        0.018145557,
        0.008855592,
        0.0041510593,
        -0.026258513,
        0.0013083718,
        0.0037096806,
        0.0158616,
        -0.03402117,
        -0.021676585,
        -0.00091866264,
        0.018215619,
        0.017921366,
        -0.035674587,
        -0.031134695,
        -0.039906215,
        -0.01738891,
        0.027365463,
        -0.014572495,
        0.013318419,
        -0.0010736706,
        0.008547328,
        0.015006867,
        -0.009381044,
        -0.032255657,
        -0.017823283,
        0.013920936,
        -0.008827569,
        -0.0014677584,
        -0.03738405
    ]
}